mlx_mhc/__init__.py
mlx_mhc/benchmark.py
mlx_mhc/mhc.py
mlx_mhc/sinkhorn.py
mlx_mhc/version.py
mlx_mhc-0.4.1.dist-info/licenses/LICENSE
mlx_mhc-0.4.1.dist-info/METADATA
mlx_mhc-0.4.1.dist-info/WHEEL
mlx_mhc-0.4.1.dist-info/top_level.txt
mlx_mhc-0.4.1.dist-info/RECORD
