Metadata-Version: 2.4
Name: mlx-mhc
Version: 0.4.1
Summary: MLX implementation of Manifold-Constrained Hyper-Connections (mHC) for Apple Silicon
Author-email: Mario Iturrino <m@r1o.ai>
Maintainer-email: Mario Iturrino <m@r1o.ai>
License: MIT
Project-URL: Homepage, https://github.com/machiabeli/mlx-mhc
Project-URL: Repository, https://github.com/machiabeli/mlx-mhc
Project-URL: Documentation, https://github.com/machiabeli/mlx-mhc#readme
Project-URL: Issues, https://github.com/machiabeli/mlx-mhc/issues
Keywords: mlx,apple silicon,deep learning,transformers,mhc,hyper-connections
Classifier: Development Status :: 3 - Alpha
Classifier: Intended Audience :: Developers
Classifier: Intended Audience :: Science/Research
Classifier: License :: OSI Approved :: MIT License
Classifier: Programming Language :: Python :: 3
Classifier: Programming Language :: Python :: 3.10
Classifier: Programming Language :: Python :: 3.11
Classifier: Programming Language :: Python :: 3.12
Classifier: Topic :: Scientific/Engineering :: Artificial Intelligence
Requires-Python: >=3.10
License-File: LICENSE
Requires-Dist: mlx>=0.10.0
Requires-Dist: numpy>=1.24.0
Provides-Extra: dev
Requires-Dist: pytest>=7.0; extra == "dev"
Requires-Dist: pytest-cov; extra == "dev"
Dynamic: license-file
